qservice/__init__.py
qservice/exemplo.py
qservice/service.py
qservice-0.3.dist-info/LICENSE
qservice-0.3.dist-info/METADATA
qservice-0.3.dist-info/WHEEL
qservice-0.3.dist-info/top_level.txt
qservice-0.3.dist-info/RECORD
