Metadata-Version: 2.1
Name: qservice
Version: 0.3
Summary: Standardize methods and create step-by-step flows
Home-page: https://github.com/rvettori/qservice
Author: Rafael Vettori
Author-email: rafael.vettori@gmail.com
License: MIT
Platform: UNKNOWN
License-File: LICENSE
